{"frameRate":30,"isGlobal":0,"name":"NYL","version":"4.5","armature":[{"slot":[{"name":"BG","parent":"BG","color":{}},{"z":1,"name":"yingleBGguang","parent":"BG","color":{}},{"z":2,"name":"xing","parent":"xing","color":{}},{"z":3,"name":"xing1","parent":"xing1","color":{}},{"z":4,"name":"xing11","parent":"xing11","color":{}},{"z":5,"name":"xing111","parent":"xing111","color":{}},{"z":6,"name":"xing1111","parent":"xing1111","color":{}},{"z":7,"name":"yingzi1","parent":"yingzi","color":{}},{"z":8,"name":"yingzi","parent":"yingzi","color":{}},{"z":9,"name":"dss_paixingzi","parent":"yingzi","color":{}},{"z":10,"name":"dss_paixingzi1","parent":"yingzi","color":{}}],"bone":[{"name":"NYLZT","transform":{}},{"length":185,"transform":{"y":125.45,"skX":-89.6301,"skY":-89.6301},"parent":"NYLZT","name":"BG"},{"length":24,"transform":{"y":10.2024,"skX":-55.6046,"skY":-55.6046,"scX":1.1,"scY":1.1,"x":-175.159},"parent":"NYLZT","name":"xing"},{"length":24,"transform":{"y":-142.861,"skX":-55.6046,"skY":-55.6046,"x":-14.6745},"parent":"NYLZT","name":"xing1"},{"length":24,"transform":{"y":-52.8783,"skX":-55.6046,"skY":-55.6046,"scX":0.9,"scY":0.9,"x":-76.8274},"parent":"NYLZT","name":"xing11"},{"length":24,"transform":{"y":-86.7377,"skX":-55.6046,"skY":-55.6046,"scX":0.7,"scY":0.7,"x":69.7887},"parent":"NYLZT","name":"xing111"},{"length":24,"transform":{"y":13.4028,"skX":-55.6046,"skY":-55.6046,"scX":1.2,"scY":1.2,"x":145.1144},"parent":"NYLZT","name":"xing1111"},{"length":62,"transform":{"y":-17.588,"skX":179.6301,"skY":179.6301,"x":114.2388},"parent":"BG","name":"yingzi"}],"aabb":{"width":522,"y":-167.28884930983003,"height":328.20981347819026,"x":-261.734079907038},"type":"Armature","frameRate":30,"ik":[],"defaultActions":[{"gotoAndPlay":"NYL"}],"skin":[{"name":"","slot":[{"display":[{"path":"dss_paixingzi","type":"image","name":"dss_paixingzi","transform":{"y":-26.9133,"skX":-90,"skY":-90,"x":-18.486}}],"name":"dss_paixingzi"},{"display":[{"path":"xing","type":"image","name":"xing","transform":{"y":1.2935,"skX":55.6046,"skY":55.6046,"x":-1.9281}}],"name":"xing1"},{"display":[{"path":"xing","type":"image","name":"xing","transform":{"y":1.2935,"skX":55.6046,"skY":55.6046,"x":-1.9281}}],"name":"xing111"},{"display":[{"path":"yingzi","type":"image","name":"yingzi","transform":{"y":-17.5288,"skX":-90,"skY":-90,"x":15.2211}}],"name":"yingzi"},{"display":[{"path":"xing","type":"image","name":"xing","transform":{"y":1.2935,"skX":55.6046,"skY":55.6046,"x":-1.9281}}],"name":"xing"},{"display":[{"path":"xing","type":"image","name":"xing","transform":{"y":1.2935,"skX":55.6046,"skY":55.6046,"x":-1.9281}}],"name":"xing1111"},{"display":[{"path":"BG","type":"image","name":"BG","transform":{"y":-1.2476,"skX":89.6301,"skY":89.6301,"x":79.5226}}],"name":"BG"},{"display":[{"path":"dss_paixingzi","type":"image","name":"dss_paixingzi","transform":{"y":-27.076,"skX":-90,"skY":-90,"scX":1.6,"x":-18.486}}],"name":"dss_paixingzi1"},{"display":[{"path":"yingzi1","type":"image","name":"yingzi1","transform":{"y":-17.4458,"skX":-90,"skY":-90,"x":14.8768}}],"name":"yingzi1"},{"display":[{"path":"yingleBGguang","type":"image","name":"yingleBGguang","transform":{"y":-6.5402,"skX":89.6301,"skY":89.6301,"x":173.7002}}],"name":"yingleBGguang"},{"display":[{"path":"xing","type":"image","name":"xing","transform":{"y":1.2935,"skX":55.6046,"skY":55.6046,"x":-1.9281}}],"name":"xing11"}]}],"name":"NYL","animation":[{"slot":[{"frame":[{"tweenEasing":0,"duration":60},{"tweenEasing":null,"duration":0}],"name":"BG"},{"frame":[{"tweenEasing":0,"duration":30},{"tweenEasing":0,"color":{"aM":46},"duration":30},{"tweenEasing":null,"duration":0}],"name":"yingleBGguang"},{"frame":[{"tweenEasing":0,"duration":12},{"tweenEasing":0,"duration":7},{"tweenEasing":0,"duration":41},{"tweenEasing":null,"duration":0}],"name":"yingzi"},{"frame":[{"displayIndex":-1,"tweenEasing":0,"duration":1},{"tweenEasing":0,"duration":30},{"tweenEasing":0,"duration":15},{"tweenEasing":0,"color":{"aM":0},"duration":1},{"displayIndex":-1,"tweenEasing":0,"color":{"aM":0},"duration":13},{"displayIndex":-1,"tweenEasing":null,"color":{"aM":0},"duration":0}],"name":"xing"},{"frame":[{"displayIndex":-1,"tweenEasing":0,"duration":3},{"tweenEasing":0,"duration":28},{"tweenEasing":0,"duration":12},{"tweenEasing":0,"color":{"aM":0},"duration":1},{"displayIndex":-1,"tweenEasing":0,"color":{"aM":0},"duration":16},{"displayIndex":-1,"tweenEasing":null,"color":{"aM":0},"duration":0}],"name":"xing1"},{"frame":[{"displayIndex":-1,"tweenEasing":0,"duration":1},{"tweenEasing":0,"duration":30},{"tweenEasing":0,"duration":21},{"tweenEasing":0,"color":{"aM":0},"duration":1},{"displayIndex":-1,"tweenEasing":0,"color":{"aM":0},"duration":7},{"displayIndex":-1,"tweenEasing":null,"color":{"aM":0},"duration":0}],"name":"xing11"},{"frame":[{"displayIndex":-1,"tweenEasing":0,"duration":4},{"tweenEasing":0,"duration":27},{"tweenEasing":0,"duration":27},{"tweenEasing":0,"color":{"aM":0},"duration":1},{"displayIndex":-1,"tweenEasing":0,"color":{"aM":0},"duration":1},{"displayIndex":-1,"tweenEasing":null,"color":{"aM":0},"duration":0}],"name":"xing111"},{"frame":[{"displayIndex":-1,"tweenEasing":0,"duration":6},{"tweenEasing":0,"duration":25},{"tweenEasing":0,"duration":19},{"tweenEasing":0,"color":{"aM":0},"duration":1},{"displayIndex":-1,"tweenEasing":0,"color":{"aM":0},"duration":9},{"displayIndex":-1,"tweenEasing":null,"color":{"aM":0},"duration":0}],"name":"xing1111"},{"frame":[{"tweenEasing":0,"color":{"aM":0},"duration":19},{"tweenEasing":0,"color":{"aM":0},"duration":15},{"tweenEasing":0,"color":{"aM":62},"duration":10},{"tweenEasing":0,"duration":16},{"tweenEasing":null,"color":{"aM":0},"duration":0}],"name":"yingzi1"},{"frame":[{"displayIndex":-1,"tweenEasing":null,"duration":19},{"tweenEasing":0,"color":{"aM":0},"duration":15},{"tweenEasing":0,"color":{"aM":65},"duration":10},{"tweenEasing":0,"duration":16},{"tweenEasing":null,"color":{"aM":0},"duration":0}],"name":"dss_paixingzi"},{"frame":[{"displayIndex":-1,"tweenEasing":0,"duration":19},{"tweenEasing":0,"color":{"aM":0},"duration":15},{"tweenEasing":0,"duration":10},{"tweenEasing":0,"duration":16},{"tweenEasing":null,"color":{"aM":0},"duration":0}],"name":"dss_paixingzi1"}],"playTimes":0,"bone":[{"frame":[{"tweenEasing":0,"transform":{},"duration":60},{"transform":{},"duration":0}],"name":"NYLZT"},{"frame":[{"tweenEasing":0,"transform":{},"duration":30},{"tweenEasing":0,"transform":{"y":-3.1216},"duration":30},{"transform":{},"duration":0}],"name":"BG"},{"frame":[{"tweenEasing":0,"transform":{},"duration":1},{"tweenEasing":0,"transform":{"y":41.156,"scX":0.5,"scY":0.5,"x":118.4253},"duration":10},{"tweenEasing":0,"transform":{"y":-73.7332,"skX":165.747,"skY":165.747,"scX":0.6556,"scY":0.6556,"x":49.4205},"duration":12},{"tweenEasing":0,"transform":{"y":-72.9168,"skX":226.6366,"skY":226.6366,"scX":0.8422,"scY":0.8422,"x":2.3374},"duration":23},{"tweenEasing":0,"transform":{"y":18.3086,"skX":343.3417,"skY":343.3417,"scX":1.2,"scY":1.2,"x":-29.5771},"duration":14},{"transform":{"y":-105.4725,"scX":1.2,"scY":1.2,"x":-55.2278},"duration":0}],"name":"xing"},{"frame":[{"tweenEasing":0,"transform":{},"duration":6},{"tweenEasing":0,"transform":{"y":-0.1021,"x":15.8122},"duration":6},{"tweenEasing":0,"transform":{"y":0.0452,"x":-6.9988},"duration":7},{"tweenEasing":0,"transform":{},"duration":4},{"tweenEasing":0,"transform":{},"duration":14},{"tweenEasing":0,"transform":{"scX":1.03,"scY":1.03},"duration":11},{"tweenEasing":0,"transform":{"scX":0.97,"scY":0.97},"duration":12},{"transform":{},"duration":0}],"name":"yingzi"},{"frame":[{"tweenEasing":0,"transform":{},"duration":3},{"tweenEasing":0,"transform":{"y":192.364,"scX":0.5,"scY":0.5,"x":-0.9641},"duration":11},{"tweenEasing":0,"transform":{"y":67.2035,"skX":165.747,"skY":165.747,"scX":0.6925,"scY":0.6925,"x":-36.0937},"duration":11},{"tweenEasing":0,"transform":{"y":25.6734,"skX":233.1105,"skY":233.1105,"scX":0.885,"scY":0.885,"x":-57.4354},"duration":18},{"tweenEasing":0,"transform":{"y":110.8893,"skX":343.3417,"skY":343.3417,"scX":1.2,"scY":1.2,"x":-80.3738},"duration":17},{"transform":{"y":-105.4725,"scX":1.2,"scY":1.2,"x":-55.2278},"duration":0}],"name":"xing1"},{"frame":[{"tweenEasing":0,"transform":{},"duration":1},{"tweenEasing":0,"transform":{"y":100.0622,"scX":0.5,"scY":0.5,"x":111.2823},"duration":10},{"tweenEasing":0,"transform":{"y":-41.8682,"skX":165.747,"skY":165.747,"scX":0.6373,"scY":0.6373,"x":162.8729},"duration":16},{"tweenEasing":0,"transform":{"y":-85.3444,"skX":235.0522,"skY":235.0522,"scX":0.8569,"scY":0.8569,"x":181.6841},"duration":25},{"tweenEasing":0,"transform":{"y":27.7901,"skX":343.3417,"skY":343.3417,"scX":1.2,"scY":1.2,"x":220.2837},"duration":8},{"transform":{"y":-105.4725,"scX":1.2,"scY":1.2,"x":-55.2278},"duration":0}],"name":"xing11"},{"frame":[{"tweenEasing":0,"transform":{},"duration":4},{"tweenEasing":0,"transform":{"y":142.3634,"scX":0.5,"scY":0.5,"x":-80.7426},"duration":10},{"tweenEasing":0,"transform":{"y":26.4073,"skX":165.747,"skY":165.747,"scX":2.1429,"scY":2.1429,"x":-71.0357},"duration":13},{"tweenEasing":0,"transform":{"y":-66.1991,"skX":218.2182,"skY":218.2182,"scX":2.4286,"scY":2.4286,"x":-49.8127},"duration":31},{"tweenEasing":0,"transform":{"y":122.3321,"skX":343.3417,"skY":343.3417,"scX":2.8571,"scY":2.8571,"x":6.3813},"duration":2},{"transform":{"y":-105.4725,"scX":1.2,"scY":1.2,"x":-55.2278},"duration":0}],"name":"xing111"},{"frame":[{"tweenEasing":0,"transform":{},"duration":6},{"tweenEasing":0,"transform":{"y":32.0986,"scX":0.5,"scY":0.5,"x":-58.7218},"duration":14},{"tweenEasing":0,"transform":{"y":-69.8575,"skX":165.747,"skY":165.747,"scX":0.7227,"scY":0.7227,"x":-11.5383},"duration":12},{"tweenEasing":0,"transform":{"y":-61.9837,"skX":236.7849,"skY":236.7849,"scX":0.9136,"scY":0.9136,"x":34.4967},"duration":18},{"tweenEasing":0,"transform":{"y":71.2299,"skX":343.3417,"skY":343.3417,"scX":1.2,"scY":1.2,"x":87.0383},"duration":10},{"transform":{"y":-105.4725,"scX":1.2,"scY":1.2,"x":-55.2278},"duration":0}],"name":"xing1111"}],"ffd":[],"ik":[],"frame":[],"name":"NYL","duration":60}]}]}