{
"skeleton": { "hash": "E28i3WjvQr8xpcj0q092RjEYv2c", "spine": "3.4.02", "width": 116, "height": 103, "images": "" },
"bones": [
	{ "name": "xingyunzhuanpanZT" }
],
"slots": [
	{ "name": "wd-zpan-1", "bone": "xingyunzhuanpanZT", "attachment": "wd-zpan-2" }
],
"skins": {
	"default": {
		"wd-zpan-1": {
			"wd-zpan-1": { "width": 116, "height": 103 },
			"wd-zpan-2": { "width": 116, "height": 103 }
		}
	}
},
"animations": {
	"xingyunzhuanpan": {
		"slots": {
			"wd-zpan-1": {
				"attachment": [
					{ "time": 0, "name": "wd-zpan-1" },
					{ "time": 0.6, "name": "wd-zpan-2" },
					{ "time": 1.2, "name": "wd-zpan-1" },
					{ "time": 1.8, "name": "wd-zpan-2" },
					{ "time": 2.2666, "name": "wd-zpan-2" }
				]
			}
		},
		"bones": {
			"xingyunzhuanpanZT": {
				"rotate": [
					{ "time": 0, "angle": 0, "curve": "stepped" },
					{ "time": 2.2666, "angle": 0 }
				],
				"translate": [
					{ "time": 0, "x": 0, "y": 0, "curve": "stepped" },
					{ "time": 2.2666, "x": 0, "y": 0 }
				],
				"scale": [
					{ "time": 0, "x": 1, "y": 1, "curve": "stepped" },
					{ "time": 2.2666, "x": 1, "y": 1 }
				]
			}
		}
	}
}
}